perfusion_pytorch/__init__.py
perfusion_pytorch/embedding.py
perfusion_pytorch/open_clip.py
perfusion_pytorch/optimizer.py
perfusion_pytorch/perfusion.py
perfusion_pytorch/save_load.py
perfusion_pytorch/data/covariance_CLIP_ViT-L-14.pt
perfusion_pytorch-0.1.23.dist-info/LICENSE
perfusion_pytorch-0.1.23.dist-info/METADATA
perfusion_pytorch-0.1.23.dist-info/WHEEL
perfusion_pytorch-0.1.23.dist-info/top_level.txt
perfusion_pytorch-0.1.23.dist-info/RECORD
