Metadata-Version: 2.1
Name: perfusion-pytorch
Version: 0.1.23
Summary: Perfusion - Pytorch
Home-page: https://github.com/lucidrains/perfusion-pytorch
Author: Phil Wang
Author-email: lucidrains@gmail.com
License: MIT
Keywords: artificial intelligence,deep learning,memory editing,text-to-image
Classifier: Development Status :: 4 - Beta
Classifier: Intended Audience :: Developers
Classifier: Topic :: Scientific/Engineering :: Artificial Intelligence
Classifier: License :: OSI Approved :: MIT License
Classifier: Programming Language :: Python :: 3.6
License-File: LICENSE
Requires-Dist: beartype
Requires-Dist: einops >=0.6.1
Requires-Dist: open-clip-torch
Requires-Dist: opt-einsum
Requires-Dist: torch >=2.0
